{
   "datetime": 1637248653,
   "donate_url": "https://www.paypal.me/asavvo01",
   "error": false,
   "filehash": "ee939e451c1c07052a23f0b730fe7656",
   "filename": "evolution_alioth-ota-rq3a.211001.001-11181520.zip",
   "forum_url": "https://forum.xda-developers.com/t/a11-official-evolution-x-v5-9-for-alioth-aliothin.4307387/",
   "id": "dec8337da2da3b14c342fe20cdee59737d9201022416e2d0a30109d61baa0172",
   "maintainer": "Aggelos Savvopoulos (DarkAngelGR)",
   "maintainer_url": "https://forum.xda-developers.com/m/darkangelgr.8065843/",
   "news_url": "https://t.me/EvolutionXOfficial",
   "size": 1684960018,
   "telegram_username": "DarkAngelGR",
   "url": "https://sourceforge.net/projects/evolution-x/files/alioth/evolution_alioth-ota-rq3a.211001.001-11181520.zip/download",
   "version": "Eleven",
   "website_url": "https://evolution-x.org"
}