{
"error":false,
"filename":"EvolutionX_cheeseburger-9.0-20190608-0246-OFFICIAL.zip",
"datetime":"1559961965",
"size":"1113620347",
"url":"https://sourceforge.net/projects/evolution-x/files/cheeseburger/EvolutionX_cheeseburger-9.0-20190608-0246-OFFICIAL.zip/download",
"filehash":"c179fcb1fa19fa6954519d64f6951676",
"version":"Pie",
"id":"6567cddd86cffbf3b4657c66c4ba7ce7e980806162ec3b26ec0c700e",
"website_url":"https://evolutionx.ml",
"news_url":"https://t.me/EvolutionXNews",
"donate_url":"https://www.paypal.me/joeyhuab",
"maintainer":"Anierin Bliss (AnierinB)",
"maintainer_url":"https://github.com/anierinbliss",
"telegram_username":"AnierinB"
}
