{
   "datetime": 1685506266,
   "donate_url": "https://www.paypal.me/yarpiin",
   "error": false,
   "filehash": "ab108dd6c0b5caa83a969bacb73fcd2c",
   "filename": "evolution_cmi-ota-tq2b.230505.005.a1-05310511.zip",
   "forum_url": "https://forum.xda-developers.com/t/rom-13-umi-cmi-official-evolution-x.4272743/",
   "id": "974883c0f1eaa1c12676d5c8daaf88d4c3b0673fcb0b3549031c8f4de94a14b1",
   "maintainer": "Slaw Handzlik (yarpiin)",
   "maintainer_url": "https://github.com/yarpiin",
   "news_url": "https://t.me/EvolutionXOfficial",
   "size": 2768785990,
   "telegram_username": "yarpiin",
   "url": "https://sourceforge.net/projects/evolution-x/files/cmi/evolution_cmi-ota-tq2b.230505.005.a1-05310511.zip/download",
   "version": "Thirteen",
   "website_url": "https://evolution-x.org"
}