{
   "datetime": 1702922096,
   "donate_url": "https://www.paypal.me/yarpiin",
   "error": false,
   "filehash": "1842652e26bbc6cad924106d4837b524",
   "filename": "evolution_cupid-ota-uq1a.231205.015-12181801-OFFICIAL.zip",
   "forum_url": "https://forum.xda-developers.com/t/rom-13-0-cupid-official-evolution-x-05-29-23.4591391",
   "id": "ad71fda0c75ef67d441f11fb203e50e729c774d466e0d1331b01f48d3edaebf7",
   "maintainer": "Slaw Handzlik (yarpiin)",
   "maintainer_url": "https://github.com/yarpiin",
   "news_url": "https://t.me/EvolutionXOfficial",
   "size": 2721783650,
   "telegram_username": "yarpiin",
   "url": "https://sourceforge.net/projects/evolution-x/files/cupid/14/evolution_cupid-ota-uq1a.231205.015-12181801-OFFICIAL.zip/download",
   "version": "Fourteen",
   "website_url": "https://evolution-x.org"
}