{
   "datetime": 1657936988,
   "donate_url": "https://Paypal.me/LucyfMorning",
   "error": false,
   "filehash": "1d5da52f090ccceffed71c2a42953597",
   "filename": "evolution_dipper-ota-sq3a.220705.003.a1-07160203-unsigned.zip",
   "forum_url": "https://forum.xda-developers.com/t/rom-official-12-1-evolution-x-snow-mi-8-dipper.4395347/",
   "id": "f0d4c8d6896ea97286ee37ea20f1c0907a3cb05d88c1c37906d426b05437191f",
   "maintainer": "Matheus C. (LuMorningStarr)",
   "maintainer_url": "https://forum.xda-developers.com/m/unnamedchronos.9127664/",
   "news_url": "https://t.me/EvolutionXOfficial",
   "size": 1637803368,
   "telegram_username": "LuMorningStarr",
   "url": "https://sourceforge.net/projects/evolution-x/files/dipper/evolution_dipper-ota-sq3a.220705.003.a1-07160203-unsigned.zip/download",
   "version": "Twelve",
   "website_url": "https://evolution-x.org"
}