{
   "datetime": 1586607528,
   "donate_url": "https://Paypal.me/asavvo01",
   "error": false,
   "filehash": "7824ecf44cd2f74de934824444d7e807",
   "filename": "EvolutionX_4.20_dipper-10.0-20200411-1219-OFFICIAL.zip",
   "forum_url": "https://forum.xda-developers.com/mi-8/development/10-0-evolution-x-v3-3-mi-8-t4006089",
   "id": "6c15f998f8ccebb4a3bf78cf353a5c1c51e4d8441f69338a128d308602406261",
   "maintainer": "Aggelos Savvopoulos (DarkAngelGR)",
   "maintainer_url": "https://forum.xda-developers.com/member.php?u=8065843",
   "news_url": "https://t.me/EvolutionXOfficial",
   "size": 1718159490,
   "telegram_username": "DarkAngelGR",
   "url": "https://sourceforge.net/projects/evolution-x/files/dipper/EvolutionX_4.20_dipper-10.0-20200411-1219-OFFICIAL.zip/download",
   "version": "Ten",
   "website_url": "https://evolution-x.org"
}
