{
   "datetime": 1673986762,
   "donate_url": "http://paypal.me/anierinb",
   "error": false,
   "filehash": "b98ca00d6380edad1a096b073b302cd0",
   "filename": "evolution_enchilada-ota-tq1a.230105.001.a2-01172020-unsigned.zip",
   "forum_url": "https://forum.xda-developers.com/t/rom-13-0_r20-official-evolution-x-7-5-01-17-2023.4488369/",
   "id": "94361117c51de9cf5ee7197d1c23c003e618d6208a5e39edc9c49f302bd0a651",
   "maintainer": "Anierin Bliss",
   "maintainer_url": "https://forum.xda-developers.com/m/anierinb.7125966/",
   "news_url": "https://t.me/EvolutionXOfficial",
   "size": 1600707979,
   "telegram_username": "Anierin_Bliss",
   "url": "https://sourceforge.net/projects/evolution-x/files/enchilada/evolution_enchilada-ota-tq1a.230105.001.a2-01172020-unsigned.zip/download/",
   "version": "Thirteen",
   "website_url": "https://evolution-x.org"
}