{
   "datetime": 1648011966,
   "donate_url": "http://paypal.me/anierinb",
   "error": false,
   "filehash": "8fa253e29cabd4db80d04d59239ca2e2",
   "filename": "evolution_enchilada-ota-sp2a.220305.013.a3-03231406-unsigned.zip",
   "forum_url": "https://forum.xda-developers.com/t/rom-12-1_r2-official-evolution-x-6-2-2-03-23-2022.3988143/",
   "id": "21d2563beaf5e6e0f9d9d87707ad86410fd5f0b3f642846691900bc3f14c5025",
   "maintainer": "Anierin Bliss",
   "maintainer_url": "https://forum.xda-developers.com/m/anierinb.7125966/",
   "news_url": "https://t.me/EvolutionXOfficial",
   "size": 1371936283,
   "telegram_username": "Anierin_Bliss",
   "url": "https://sourceforge.net/projects/evolution-x/files/enchilada/evolution_enchilada-ota-sp2a.220305.013.a3-03231406-unsigned.zip/download",
   "version": "Twelve",
   "website_url": "https://evolution-x.org"
}
