{
   "datetime": 1653154521,
   "donate_url": "http://paypal.me/anierinb",
   "error": false,
   "filehash": "eb757a7fd42f1e6cb76e8dfaa1269728",
   "filename": "evolution_enchilada-ota-sp2a.220505.002-05220236-unsigned.zip",
   "forum_url": "https://forum.xda-developers.com/t/rom-12-1_r5-official-evolution-x-6-4-05-22-2022.3988143/",
   "id": "94ad6e91507dae4c213edae21bd5308e12b5bc255eed118061e26ed20b8d9d56",
   "maintainer": "Anierin Bliss",
   "maintainer_url": "https://forum.xda-developers.com/m/anierinb.7125966/",
   "news_url": "https://t.me/EvolutionXOfficial",
   "size": 1406487984,
   "telegram_username": "Anierin_Bliss",
   "url": "https://sourceforge.net/projects/evolution-x/files/enchilada/evolution_enchilada-ota-sp2a.220505.002-05220236-unsigned.zip/download",
   "version": "Twelve",
   "website_url": "https://evolution-x.org"
}