{
"error":false,
"filename":"EvolutionX_ether-9.0-20190720-0149-OFFICIAL.zip",
"datetime":1563587360,
"size": 829820773,
"url":"https://sourceforge.net/projects/evolution-x/files/ether/EvolutionX_ether-9.0-20190720-0149-OFFICIAL.zip/download",
"filehash":"d8f9b1f195de69f315732fc716e04f78",
"version":"Pie",
"id":"694535348b53b24e2e7c52fdbff66ea9fe8fc18f6a2cab33639ae05df3a4b77b",
"website_url":"https://evolution-x.org",
"news_url":"https://t.me/EvolutionXOfficial",
"donate_url":"https://www.paypal.me/joeyhuab",
"maintainer":"Anierin Bliss (AnierinB)",
"maintainer_url":"https://github.com/anierinbliss",
"telegram_username":"AnierinB",
"forum_url":"https://forum.xda-developers.com/nextbit-robin/development/rom-evolution-x-t3927148"
}
