{
         "error":false,
         "filename": "EvolutionX_ks01ltexx-9.0-20190728-2153-OFFICIAL.zip",
         "datetime": 1564350803,
         "size": 564140334,
         "url":"https://sourceforge.net/projects/evolution-x/files/ks01ltexx/EvolutionX_ks01ltexx-9.0-20190728-2153-OFFICIAL.zip/download",
         "filehash":"fcd65943e54f2b25ad866afa072e26ad",
         "version":"Pie",
         "id": "2e6e4ab6ef37db73a8c9d3303153b525a5a8eb2455c65418f6e4f4aa0ee17f0e",
         "website_url":"https://evolution-x.org",
         "news_url":"https://t.me/EvolutionXOfficial",
         "donate_url":"https://Paypal.me/joeyhuab",
         "maintainer":"1bdellatiF (darkness)",
         "maintainer_url":"https://forum.xda-developers.com/member.php?u=6459107",
         "telegram_username":"taoubi",
         "forum_url":"https://forum.xda-developers.com/galaxy-s4/i9506-develop/rom-evolution-x-t3947486"
}
