{
   "datetime": 1596912192,
   "donate_url": "https://www.paypal.me/hdsrivastava",
   "error": false,
   "filehash": "00b419b4a361ccd04ed060f2d7852124",
   "filename": "EvolutionX_4.6_laurel_sprout-10.0-20200808-1844-OFFICIAL.zip",
   "forum_url": "https://forum.xda-developers.com/mi-a3/development/10-evolutionx-4-3-07-05-2020-t4095609",
   "id": "32c5f33d420feb5beffb9ea6870e95a2713675ff89f9a9ba7dea5ef32d8656ff",
   "maintainer": "oddlyspaced",
   "maintainer_url": "https://forum.xda-developers.com/member.php?u=9807173",
   "news_url": "https://t.me/EvolutionXOfficial",
   "size": 1544905322,
   "telegram_username": "oddlyspaced",
   "url": "https://sourceforge.net/projects/evolution-x/files/laurel_sprout/EvolutionX_4.6_laurel_sprout-10.0-20200808-1844-OFFICIAL.zip/download",
   "version": "Ten",
   "website_url": "https://evolution-x.org"
}