{
   "datetime": 1690887454,
   "donate_url": "https://linktr.ee/shaughzam",
   "error": false,
   "filehash": "d0390ab8213dba7fb24d428103c45804",
   "filename": "evolution_marble-ota-tq3c.230705.001.c2-08011059-unsigned.zip",
   "forum_url": "https://forum.xda-developers.com/t/rom-13-0_r52-marble-official-evolution-x-06-21-23.4597991",
   "id": "334d4269158b99eafc4a933da8a912ee60e48c3834b5e230c68b0d298f8cd473",
   "maintainer": "Joey",
   "maintainer_url": "https://forum.xda-developers.com/m/joeyhuab.4936496",
   "news_url": "https://t.me/EvolutionXOfficial",
   "size": 2999404086,
   "telegram_username": "shaughzam",
   "url": "https://sourceforge.net/projects/evolution-x/files/marble/13/evolution_marble-ota-tq3c.230705.001.c2-08011059-unsigned.zip/download",
   "version": "Thirteen",
   "website_url": "https://evolution-x.org"
}