{
   "datetime": 1690688669,
   "donate_url": "https://www.paypal.me/Sonal18",
   "error": false,
   "filehash": "7fcef026ca59a8def79c68ac17a4ed4e",
   "filename": "evolution_miatoll-ota-tq3c.230705.001.c2-07300349-unsigned.zip",
   "forum_url": "https://forum.xda-developers.com/m/sonalsingh18.8425394",
   "id": "08b2e21bd804d8d134b20b320cead013b03123468d2546e3ead502dc490b6134",
   "maintainer": "Sonal Singh",
   "maintainer_url": "https://t.me/EvolutionXMiatoll",
   "news_url": "https://t.me/EvolutionXOfficial",
   "size": 2283491407,
   "telegram_username": "SonalSingh18",
   "url": "https://sourceforge.net/projects/evolution-x/files/miatoll/13/evolution_miatoll-ota-tq3c.230705.001.c2-07300349-unsigned.zip/download",
   "version": "Thirteen",
   "website_url": "https://evolution-x.org"
}