{
   "datetime": 1606599041,
   "donate_url": "",
   "error": false,
   "filehash": "c2677a7e6ebd87daeb533531cde5a46b",
   "filename": "EvolutionX_5.1_miatoll-11-20201128-2133-OFFICIAL.zip",
   "forum_url": "",
   "id": "c592af64dd794f78d51b389c503da9a1e2a2b7b547749fb7fa6f94b5c45ad0e5",
   "maintainer": "Ahmed Tohamy (Agmad)",
   "maintainer_url": "https://forum.xda-developers.com/member.php?u=8386267",
   "news_url": "https://t.me/EvolutionXOfficial",
   "size": 1717078027,
   "telegram_username": "Ahmed_Tohamy",
   "url": "https://sourceforge.net/projects/evolution-x/files/miatoll/EvolutionX_5.1_miatoll-11-20201128-2133-OFFICIAL.zip/download",
   "version": "Eleven",
   "website_url": "https://evolution-x.org"
}
