{
   "datetime": 1618612406,
   "donate_url": "https://www.paypal.me/ahmedtohamy1",
   "error": false,
   "filehash": "356c20535f771addc61f0a26ca61c218",
   "filename": "EvolutionX_5.6_miatoll-11-20210416-2236-OFFICIAL.zip",
   "forum_url": "",
   "id": "cbc28dfa47ad501bc7d5495b0fcae2a58191220e21d3a433e498a15542b341cd",
   "maintainer": "Ahmed Tohamy (Agmad)",
   "maintainer_url": "https://forum.xda-developers.com/member.php?u=8386267",
   "news_url": "https://t.me/EvolutionXOfficial",
   "size": 1909021676,
   "telegram_username": "Ahmed_Tohamy",
   "url": "https://sourceforge.net/projects/evolution-x/files/miatoll/EvolutionX_5.6_miatoll-11-20210416-2236-OFFICIAL.zip/download",
   "version": "Eleven",
   "website_url": "https://evolution-x.org"
}
