{
   "datetime": 1650807065,
   "donate_url": "https://www.paypal.me/jjpprrrr",
   "error": false,
   "filehash": "c2e211153443ed95ef63e5b734b2fc9e",
   "filename": "evolution_polaris-ota-sp2a.220405.004-04240931-unsigned.zip",
   "forum_url": "https://forum.xda-developers.com/t/4101193/",
   "id": "630b5465472a3d67a3c1e5cd05fde9b5c0f9fc85f00c76f37f27f038d5f8b539",
   "maintainer": "Chenyang Zhong (jjpprrrr)",
   "maintainer_url": "https://forum.xda-developers.com/m/jjpprrrr.9585779/",
   "news_url": "https://t.me/EvolutionXOfficial",
   "size": 1726053777,
   "telegram_username": "jjpprrrr",
   "url": "https://sourceforge.net/projects/evolution-x/files/polaris/evolution_polaris-ota-sp2a.220405.004-04240931-unsigned.zip/download",
   "version": "Twelve",
   "website_url": "https://evolution-x.org"
}