{
   "datetime": 1684641538,
   "donate_url": "https://linktr.ee/Stallix",
   "error": false,
   "filehash": "0c9485c716f0e31c72c7c4eea44e5189",
   "filename": "evolution_raphael-ota-tq2b.230505.005.a1-05210401-unsigned.zip",
   "forum_url": "https://forum.xda-developers.com/t/rom-13-0_r16-raphael-official-evolution-x-12-13-22.4481179/",
   "id": "27bca68cee6a49c05345917e88c2ba91c26eb811f766e27e2ff7baba5c806fcf",
   "maintainer": "Joey Huab (Stallix)",
   "maintainer_url": "https://forum.xda-developers.com/m/joeyhuab.4936496",
   "news_url": "https://t.me/EvolutionXOfficial",
   "size": 2155819758,
   "telegram_username": "Stallix",
   "url": "https://sourceforge.net/projects/evolution-x/files/raphael/evolution_raphael-ota-tq2b.230505.005.a1-05210401-unsigned.zip/download",
   "version": "Thirteen",
   "website_url": "https://evolution-x.org"
}