{
   "datetime": 1702516043,
   "donate_url": "http://paypal.me/anierinb",
   "error": false,
   "filehash": "6003c9841a29b0a62db3fd5733fbe325",
   "filename": "evolution_raven-ota-uq1a.231205.015-12140109-OFFICIAL.zip",
   "forum_url": "https://xdaforums.com/t/rom-14-0_r17-official-evolution-x-8-1-12-13-2023.4547009/",
   "id": "2f239c24de98acd7dacf015b5067205031ec0eaabc2b29e96dc7df2420228044",
   "maintainer": "Anierin Bliss",
   "maintainer_url": "https://forum.xda-developers.com/m/anierinb.7125966",
   "news_url": "https://t.me/EvolutionXOfficial",
   "size": 2590598517,
   "telegram_username": "Anierin_Bliss",
   "url": "https://sourceforge.net/projects/evolution-x/files/raven/14/evolution_raven-ota-uq1a.231205.015-12140109-OFFICIAL.zip/download/",
   "version": "Fourteen",
   "website_url": "https://evolution-x.org"
}
