{
   "datetime": 1703851101,
   "donate_url": "https://paypal.me/sukrut2612",
   "error": false,
   "filehash": "eb394b128b66338ff1c2792b4f781528",
   "filename": "evolution_redfin-ota-uq1a.231205.015-12291731-OFFICIAL.zip",
   "forum_url": "https://xdaforums.com/t/rom-14-0-0_r17-redfin-official-evolution-x-12-29-23.4578661/",
   "id": "e6ea7f4565c49af2498e350df7bf53566d5980e0d4cb1500a52bc7f2a2eea660",
   "maintainer": "Sukrut Kelkar",
   "maintainer_url": "https://xdaforums.com/m/sukrut4778.9573489/",
   "news_url": "https://t.me/EvolutionXOfficial",
   "size": 2154920238,
   "telegram_username": "Sukrut4778",
   "url": "https://sourceforge.net/projects/evolution-x/files/redfin/14/evolution_redfin-ota-uq1a.231205.015-12291731-OFFICIAL.zip/download",
   "version": "Fourteen",
   "website_url": "https://evolution-x.org"
}