{
   "datetime": "1680421596",
   "donate_url": "https://paypal.me/abhis699",
   "error": false,
   "filehash": "31c13367fbe1b6fc649ae5e5e3f3d191",
   "filename": "evolution_rmx3371-ota-tq2a.230305.008.c1-04061157-unsigned.zip",
   "forum_url": "",
   "id": "22a6e81f51f1e167f40c418e2140b1e922284ff6de1e110e33b7395bd2344717",
   "maintainer": "Abhishek Shukla",
   "maintainer_url": "https://github.com/abhis699",
   "news_url": "https://t.me/EvolutionXOfficial",
   "size": "2274333923",
   "telegram_username": "Abhishek699",
   "url": "https://sourceforge.net/projects/evolution-x/files/rmx3371/evolution_rmx3371-ota-tq2a.230305.008.c1-04061157-unsigned.zip/download",
   "version": "Thirteen",
   "website_url": "https://evolution-x.org"
}