{
   "error": false,
   "filename": "EvolutionX_4.0_sanders-10.0-20200108-1422-OFFICIAL.zip",
   "datetime": 1578493256,
   "size": 1278682732,
   "url": "https://sourceforge.net/projects/evolution-x/files/sanders/EvolutionX_4.0_sanders-10.0-20200108-1422-OFFICIAL.zip/download",
   "filehash": "4b6ef772da4162162a317fd192b7e043",
   "version": "Ten",
   "id": "c089781f739baa6170115dadb8d56da19c9d1eac02d7fbb1cb82f8f371acfad6",
   "website_url": "https://evolution-x.org",
   "news_url": "https://t.me/EvolutionXOfficial",
   "donate_url": "https://Paypal.me/marshmello61",
   "maintainer": "Mayur Varde",
   "maintainer_url": "https://forum.xda-developers.com/member.php?u=9134270",
   "telegram_username": "marshmello_61",
   "forum_url": "https://forum.xda-developers.com/moto-g5s-plus/development/rom-evolution-x-4-0-moto-g5s-plus-t4031813"
}
