{
   "datetime": 1682839348,
   "donate_url": "https://paypal.me/NTCMinh0310",
   "error": false,
   "filehash": "2a1df83aefe97ddfe384062df4af7d7f",
   "filename": "evolution_star2lte-ota-tq2a.230405.003.e1-04300325-unsigned.zip",
   "forum_url": "https://forum.xda-developers.com/t/rom-13-starlte-star2lte-official-evolution-x-08-23-2022.4483439/",
   "id": "85b624c4079d5e34e5898499a98bfa3c9ae150e67c5a8782b6b822e30966a39a",
   "maintainer": "Pham Nguyen Gia Khiem (Cyder)",
   "maintainer_url": "https://forum.xda-developers.com/m/cyderxda.11350071/",
   "news_url": "https://t.me/EvolutionXOfficial",
   "size": 1742264995,
   "telegram_username": "Cyderxxv",
   "url": "https://sourceforge.net/projects/evolution-x/files/star2lte/evolution_star2lte-ota-tq2a.230405.003.e1-04300325-unsigned.zip/download",
   "version": "Thirteen",
   "website_url": "https://evolution-x.org"
}