{
   "datetime": 1688673389,
   "donate_url": "https://www.paypal.me/tedomi270503",
   "error": false,
   "filehash": "74dbd821dc4691e17e21a287a87b0d7f",
   "filename": "evolution_tulip-ota-tq3a.230705.001.b4-07070312-unsigned.zip",
   "forum_url": "https://forum.xda-developers.com/t/rom-13-tulip-official-evolution-x-7-6-2-27-02-23.4463135",
   "id": "0ca748b080ab0787604959bf9fce5721bd9be19b49c1b3004233f1630e42ca10",
   "maintainer": "Le Hong Duc (tedomi2705)",
   "maintainer_url": "https://t.me/tedomi2705",
   "news_url": "https://t.me/EvolutionXOfficial",
   "size": 1538652426,
   "telegram_username": "tedomi2705",
   "url": "https://sourceforge.net/projects/evolution-x/files/tulip/13/evolution_tulip-ota-tq3a.230705.001.b4-07070312-unsigned.zip/download",
   "version": "Thirteen",
   "website_url": "https://evolution-x.org"
}