{
   "datetime": 1590754269,
   "donate_url": "https://www.paypal.me/Dobsgw",
   "error": false,
   "filehash": "72efbc47f96df0933eb6fe2a57312419",
   "filename": "EvolutionX_4.3_twolip-10.0-20200529-1212-OFFICIAL.zip",
   "forum_url": "https://forum.xda-developers.com/redmi-note-6-pro/development/rom-evolutionx-4-1-unofficial-tulip-t4048893",
   "id": "57c7e5fc716f2bf0d017c049c80063e7ee3beae760538be67d1599ebf88b0fd8",
   "maintainer": "Dobgsw",
   "maintainer_url": "https://forum.xda-developers.com/member.php?u=7144653",
   "news_url": "https://t.me/EvolutionXOfficial",
   "size": 1514511622,
   "telegram_username": "Dobsgw",
   "url": "https://sourceforge.net/projects/evolution-x/files/twolip/EvolutionX_4.3_twolip-10.0-20200529-1212-OFFICIAL.zip/download",
   "version": "Ten",
   "website_url": "https://evolution-x.org"
}