{
   "datetime": 1664899675,
   "donate_url": "https://www.paypal.me/yarpiin",
   "error": false,
   "filehash": "46712596b5df01d555444177809d8173",
   "filename": "evolution_umi-ota-tp1a.221005.003-10041708.zip",
   "forum_url": "https://forum.xda-developers.com/t/rom-13-umi-cmi-official-evolution-x.4272743/",
   "id": "78211b47fc457f0e6c85e49861b65721637ab850da557ccfa6dfd1e6bd6ea3bb",
   "maintainer": "Slaw Handzlik (yarpiin)",
   "maintainer_url": "https://github.com/yarpiin",
   "news_url": "https://t.me/EvolutionXOfficial",
   "size": 2384825904,
   "telegram_username": "yarpiin",
   "url": "https://sourceforge.net/projects/evolution-x/files/umi/evolution_umi-ota-tp1a.221005.003-10041708.zip/download",
   "version": "Thirteen",
   "website_url": "https://evolution-x.org"
}