{
   "datetime": 1655662511,
   "donate_url": "https://paypal.me/destiny88end",
   "error": false,
   "filehash": "f5dda6826054997a47a2845babda124a",
   "filename": "evolution_vayu-ota-sq3a.220605.009.b1-06200317.zip",
   "forum_url": "https://forum.xda-developers.com/t/rom-12-official-evolution-x-poco-x3-pro-vayu.4368817",
   "id": "1d93e19003f7da5d337c64d96bd1e2fda891bd503437874cf2a47935521f2e4c",
   "maintainer": "Fikri A. (elizabethangelalorenza)",
   "maintainer_url": "https://forum.xda-developers.com/m/elizabethangelalorenza.7923660",
   "news_url": "https://t.me/EvolutionXOfficial",
   "size": 1740908799,
   "telegram_username": "elizabethangelalorenza",
   "url": "https://sourceforge.net/projects/evolution-x/files/vayu/evolution_vayu-ota-sq3a.220605.009.b1-06200317.zip/download",
   "version": "Twelve",
   "website_url": "https://evolution-x.org"
}