{
   "datetime": 1685268865,
   "donate_url": "https://linktr.ee/Stallix",
   "error": false,
   "filehash": "3dc46c9d897a21928b9d6d878a764fa0",
   "filename": "evolution_venus-ota-tq2b.230505.005.a1-05281014-unsigned.zip",
   "forum_url": "https://forum.xda-developers.com/t/rom-13-0_r16-venus-official-evolution-x-12-13-22.4490535/",
   "id": "37d9f323c8df23c8387ce5a44659b813e643e53c175662b3cb5773d5c7c5f679",
   "maintainer": "Joey Huab (Stallix)",
   "maintainer_url": "https://forum.xda-developers.com/m/joeyhuab.4936496",
   "news_url": "https://t.me/EvolutionXOfficial",
   "size": 2557787471,
   "telegram_username": "Stallix",
   "url": "https://sourceforge.net/projects/evolution-x/files/venus/evolution_venus-ota-tq2b.230505.005.a1-05281014-unsigned.zip/download",
   "version": "Thirteen",
   "website_url": "https://evolution-x.org"
}