{
         "error":false,
         "filename":"EvolutionX_vince-9.0-20190607-1251-OFFICIAL.zip",
         "datetime": 1559911822,
         "size": 945439418,
         "url":"https://sourceforge.net/projects/evolution-x/files/vince/EvolutionX_vince-9.0-20190607-1251-OFFICIAL.zip/download",
         "filehash":"c1f8e419fa9a16891e74507ec7323843",
         "version":"Pie",
         "id":"27bf0781e564dfbd47f520ba18b59dcbec5320c44b8168e5fe46e95367f4f0d4",
         "website_url":"https://evolutionx.ml",
         "news_url":"https://t.me/EvolutionXNews",
         "donate_url":"https://Paypal.me/joeyhuab",
         "maintainer":"Naveen Achari",
         "maintainer_url":"https://t.me/Naveenkumarachari",
         "telegram_username":"Naveenkumarachari",
         "forum_url":"https://forum.xda-developers.com/member.php?u=9697924"
}
