{
   "datetime": "1593012933",
   "donate_url": "https://PayPal.me/vivekachoooz",
   "error": false,
   "filehash": "8b1cde6810a143796e0bd85e9d56e72e",
   "filename": "EvolutionX_4.4_X00TD-10.0-20200624-1536-OFFICIAL.zip",
   "forum_url": "https://forum.xda-developers.com/asus-zenfone-max-pro-m1/development/x00t-evolution-x-4-1-asus-zenfone-max-t4079671",
   "id": "4a1b5a6426534a913284078052fd56af7d04c590ffebd5109d7bda6d02cd8488",
   "maintainer": "Achooz",
   "maintainer_url": "https://forum.xda-developers.com/member.php?u=10449035",
   "news_url": "https://t.me/EvolutionXOfficial",
   "size": 1283950297,
   "telegram_username": "vivekachooz",
   "url": "https://sourceforge.net/projects/evolution-x/files/X00TD/EvolutionX_4.4_X00TD-10.0-20200624-1536-OFFICIAL.zip/download",
   "version": "Ten",
   "website_url": "https://evolution-x.org"
}