{
   "error": false,
   "filename": "EvolutionX_2.1_X01BD-9.0-20190908-1844-OFFICIAL.zip",
   "datetime": 1567968118,
   "size": 1040689834,
   "url": "https://sourceforge.net/projects/evolution-x/files/X01BD/EvolutionX_2.1_X01BD-9.0-20190908-1844-OFFICIAL.zip/download",
   "filehash": "ccec79d86b8971acb1adde743a6c69b7",
   "version": "Pie",
   "id": "473f0f914a1109d061a8b9b0b7d234b57b5b94def2dc32d11076ba6ea70b79b2",
   "website_url": "https://evolution-x.org",
   "news_url": "https://t.me/EvolutionXOfficial",
   "donate_url": "https://www.paypal.me/ashokvarma32",
   "maintainer": "Ashok_Varma",
   "maintainer_url": "https://github.com/ashokmini",
   "telegram_username": "TheAshokVarma",
   "forum_url": "https://forum.xda-developers.com/max-pro-m2/development/9-0-rom-evolution-x-t3922411"
}
