{
   "datetime": "1584065487",
   "donate_url": "https://www.paypal.me/dartdental",
   "error": false,
   "filehash": "80e8fd1e650b736ee0c080123e221068",
   "filename": "EvolutionX_4.1.69_X01BD-10.0-20200313-0212-OFFICIAL.zip",
   "forum_url": "https://forum.xda-developers.com/max-pro-m2/development/android-10-evolutionx-t4052793",
   "id": "080bf64ab688e7f8e7125170e4f45893d7eb5c177a96ef87704bf729e5d03224",
   "maintainer": "Vyom Desai",
   "maintainer_url": "https://forum.xda-developers.com/member.php?u=8876697",
   "news_url": "https://t.me/EvolutionXOfficial",
   "size": "1461251030",
   "telegram_username": "CannedShroudted",
   "url": "https://sourceforge.net/projects/evolution-x/files/X01BD/EvolutionX_4.1.69_X01BD-10.0-20200313-0212-OFFICIAL.zip/download",
   "version": "Ten",
   "website_url": "https://evolution-x.org"
}