{
   "datetime": "1595815557",
   "donate_url": "https://www.paypal.me/sg4778",
   "error": false,
   "filehash": "74b04e7f45eb32008eb1d410792058b6",
   "filename": "EvolutionX_4.5_x2-10.0-20200727-0206-OFFICIAL.zip",
   "forum_url": "https://forum.xda-developers.com/realme-x2/development/rom-evolution-x-4-4-t4124517",
   "id": "6be66cbe4d6af7d4894e76597e85457c694f5d009d0c2aaaeb62e89029364930",
   "maintainer": "Sukrut4778",
   "maintainer_url": "https://forum.xda-developers.com/member.php?u=9573489",
   "news_url": "https://t.me/EvolutionXOfficial",
   "size": 1689760008,
   "telegram_username": "Sukrut4778",
   "url": "https://sourceforge.net/projects/evolution-x/files/x2/EvolutionX_4.5_x2-10.0-20200727-0206-OFFICIAL.zip/download",
   "version": "Ten",
   "website_url": "https://evolution-x.org"
}